MANIFEST.in
README.md
requirements-dev.txt
requirements.txt
setup.py
sat_stac.egg-info/PKG-INFO
sat_stac.egg-info/SOURCES.txt
sat_stac.egg-info/dependency_links.txt
sat_stac.egg-info/entry_points.txt
sat_stac.egg-info/requires.txt
sat_stac.egg-info/top_level.txt
satstac/__init__.py
satstac/catalog.py
satstac/cli.py
satstac/collection.py
satstac/config.py
satstac/item.py
satstac/itemcollection.py
satstac/thing.py
satstac/utils.py
satstac/version.py
test/test_catalog.py
test/test_cli.py
test/test_collection.py
test/test_item.py
test/test_itemcollection.py
test/test_main.py
test/test_thing.py
test/test_utils.py